proxylib/__init__.py
proxylib/env.py
proxylib/netutils.py
proxylib/proxy.py
proxylib/requests.py
proxylib/os/__init__.py
proxylib/os/nt.py
proxylib/pac/__init__.py
proxylib/pac/javascript.py
proxylib-0.5.9.dist-info/METADATA
proxylib-0.5.9.dist-info/WHEEL
proxylib-0.5.9.dist-info/licenses/LICENSE
proxylib-0.5.9.dist-info/RECORD
